traffic_light.v
`timescale 1ns / 1ps

// State machine for traffic light control
module traffic_light(
    input clk,
    input rst,
    output reg [2:0] lights
);

    // State encoding
    localparam RED     = 2'b00,
               GREEN   = 2'b01,
               YELLOW  = 2'b10;

    // Light outputs
    localparam RED_LIGHT    = 3'b001,
               GREEN_LIGHT  = 3'b010,
               YELLOW_LIGHT = 3'b100,
               OFF_ALL      = 3'b000;

    reg [1:0] state;
    reg [24:0] timer;

    // State transition logic
    always @(posedge clk) begin

        if (rst) begin
            state <= RED;
            timer <= 0;
            lights <= RED_LIGHT;
        end
        else begin

            timer <= timer + 1;

            case(state)

                RED: begin
                    lights <= RED_LIGHT;

                    if (timer >= 10) begin
                        state <= GREEN;
                        timer <= 0;
                    end
                end

                GREEN: begin
                    lights <= GREEN_LIGHT;

                    if (timer >= 10) begin
                        state <= YELLOW;
                        timer <= 0;
                    end
                end

                YELLOW: begin
                    lights <= YELLOW_LIGHT;

                    if (timer >= 10) begin
                        state <= RED;
                        timer <= 0;
                    end
                end

                default: begin
                    state <= RED;
                    lights <= OFF_ALL;
                end

            endcase
        end
    end

endmodule

tb_traffic_light.v
`timescale 1ns / 1ps

module tb_traffic_light;

    reg clk;
    reg rst;
    wire [2:0] lights;

    traffic_light uut (
        .clk(clk),
        .rst(rst),
        .lights(lights)
    );

    // Clock generation
    initial clk = 0;
    always #5 clk = ~clk;

    // Test sequence
    initial begin

        rst = 1;

        @(posedge clk);
        @(posedge clk);

        rst = 0;

        repeat(50) @(posedge clk);

        $display("Final lights = %b", lights);

        $finish;

    end

    // GTKWave dump
    initial begin
        $dumpfile("traffic_light.vcd");
        $dumpvars(0, tb_traffic_light);
    end

    // Monitor
    initial begin
        $monitor("Time=%0t state lights=%b",
                  $time, lights);
    end

endmodule

traffic_light.vcd
$date
	Wed May 13 21:43:56 2026
$end
$version
	Icarus Verilog
$end
$timescale
	1ps
$end
$scope module tb_traffic_light $end
$var wire 3 ! lights [2:0] $end
$var reg 1 " clk $end
$var reg 1 # rst $end
$scope module uut $end
$var wire 1 " clk $end
$var wire 1 # rst $end
$var parameter 2 $ GREEN $end
$var parameter 3 % GREEN_LIGHT $end
$var parameter 3 & OFF_ALL $end
$var parameter 2 ' RED $end
$var parameter 3 ( RED_LIGHT $end
$var parameter 2 ) YELLOW $end
$var parameter 3 * YELLOW_LIGHT $end
$var reg 3 + lights [2:0] $end
$var reg 2 , state [1:0] $end
$var reg 25 - timer [24:0] $end
$upscope $end
$upscope $end
$enddefinitions $end
$comment Show the parameter values. $end
$dumpall
b100 *
b10 )
b1 (
b0 '
b0 &
b10 %
b1 $
$end
#0
$dumpvars
bx -
bx ,
bx +
1#
0"
bx !
$end
#5000
b1 !
b1 +
b0 -
b0 ,
1"
#10000
0"
#15000
0#
1"
#20000
0"
#25000
b1 -
1"
#30000
0"
#35000
b10 -
1"
#40000
0"
#45000
b11 -
1"
#50000
0"
#55000
b100 -
1"
#60000
0"
#65000
b101 -
1"
#70000
0"
#75000
b110 -
1"
#80000
0"
#85000
b111 -
1"
#90000
0"
#95000
b1000 -
1"
#100000
0"
#105000
b1001 -
1"
#110000
0"
#115000
b1010 -
1"
#120000
0"
#125000
b1 ,
b0 -
1"
#130000
0"
#135000
b10 !
b10 +
b1 -
1"
#140000
0"
#145000
b10 -
1"
#150000
0"
#155000
b11 -
1"
#160000
0"
#165000
b100 -
1"
#170000
0"
#175000
b101 -
1"
#180000
0"
#185000
b110 -
1"
#190000
0"
#195000
b111 -
1"
#200000
0"
#205000
b1000 -
1"
#210000
0"
#215000
b1001 -
1"
#220000
0"
#225000
b1010 -
1"
#230000
0"
#235000
b10 ,
b0 -
1"
#240000
0"
#245000
b100 !
b100 +
b1 -
1"
#250000
0"
#255000
b10 -
1"
#260000
0"
#265000
b11 -
1"
#270000
0"
#275000
b100 -
1"
#280000
0"
#285000
b101 -
1"
#290000
0"
#295000
b110 -
1"
#300000
0"
#305000
b111 -
1"
#310000
0"
#315000
b1000 -
1"
#320000
0"
#325000
b1001 -
1"
#330000
0"
#335000
b1010 -
1"
#340000
0"
#345000
b0 ,
b0 -
1"
#350000
0"
#355000
b1 !
b1 +
b1 -
1"
#360000
0"
#365000
b10 -
1"
#370000
0"
#375000
b11 -
1"
#380000
0"
#385000
b100 -
1"
#390000
0"
#395000
b101 -
1"
#400000
0"
#405000
b110 -
1"
#410000
0"
#415000
b111 -
1"
#420000
0"
#425000
b1000 -
1"
#430000
0"
#435000
b1001 -
1"
#440000
0"
#445000
b1010 -
1"
#450000
0"
#455000
b1 ,
b0 -
1"
#460000
0"
#465000
b10 !
b10 +
b1 -
1"
#470000
0"
#475000
b10 -
1"
#480000
0"
#485000
b11 -
1"
#490000
0"
#495000
b100 -
1"
#500000
0"
#505000
b101 -
1"
#510000
0"
#515000
b110 -
1"
